eiogram/__init__.py
eiogram/client/__init__.py
eiogram/client/_bot.py
eiogram/client/methods/__init__.py
eiogram/client/methods/_answer_callback.py
eiogram/client/methods/_answer_inline_query.py
eiogram/client/methods/_base.py
eiogram/client/methods/_delete_messages.py
eiogram/client/methods/_delete_webhook.py
eiogram/client/methods/_edit_message.py
eiogram/client/methods/_edit_message_caption.py
eiogram/client/methods/_edit_message_reply_markup.py
eiogram/client/methods/_edit_message_text.py
eiogram/client/methods/_forward_message.py
eiogram/client/methods/_get_chat_member.py
eiogram/client/methods/_get_me.py
eiogram/client/methods/_get_updates.py
eiogram/client/methods/_pin_message.py
eiogram/client/methods/_restrict_user.py
eiogram/client/methods/_send_message.py
eiogram/client/methods/_send_photo.py
eiogram/client/methods/_set_my_commands.py
eiogram/client/methods/_set_webhook.py
eiogram/dispatcher/__init__.py
eiogram/dispatcher/_dispatcher.py
eiogram/dispatcher/_router.py
eiogram/dispatcher/_handlers/__init__.py
eiogram/dispatcher/_handlers/_base.py
eiogram/dispatcher/_handlers/_callback_query.py
eiogram/dispatcher/_handlers/_error.py
eiogram/dispatcher/_handlers/_fallback.py
eiogram/dispatcher/_handlers/_inline_query.py
eiogram/dispatcher/_handlers/_message.py
eiogram/dispatcher/_handlers/_middleware.py
eiogram/filters/__init__.py
eiogram/filters/_base.py
eiogram/filters/_chat_type.py
eiogram/filters/_command.py
eiogram/filters/_contact.py
eiogram/filters/_data.py
eiogram/filters/_photo.py
eiogram/filters/_regax.py
eiogram/filters/_shared.py
eiogram/filters/_state.py
eiogram/filters/_text.py
eiogram/middleware/__init__.py
eiogram/middleware/_base.py
eiogram/state/__init__.py
eiogram/state/_manager.py
eiogram/state/_state.py
eiogram/state/storage/__init__.py
eiogram/state/storage/_base.py
eiogram/state/storage/_memory.py
eiogram/types/__init__.py
eiogram/types/_base.py
eiogram/types/_bot_command.py
eiogram/types/_callback_query.py
eiogram/types/_chat.py
eiogram-4.1.0.dist-info/licenses/LICENSE
eiogram-4.1.0.dist-info/METADATA
eiogram-4.1.0.dist-info/WHEEL
eiogram-4.1.0.dist-info/top_level.txt
eiogram-4.1.0.dist-info/RECORD
