Metadata-Version: 2.4
Name: eiogram
Version: 4.1.0
Summary: A Python library for
Author-email: Erfan <erfjab@gmail.com>
License: MIT
Project-URL: Homepage, https://github.com/erfjab/eiogram
Classifier: Programming Language :: Python :: 3.11
Classifier: License :: OSI Approved :: MIT License
Classifier: Operating System :: OS Independent
Requires-Python: >=3.11
License-File: LICENSE
Requires-Dist: aiohttp>=3.9.0
Requires-Dist: ujson>=5.9.0
Dynamic: license-file
